sphinxjp.themes.gopher-0.2.3-py3.7-nspkg.pth
sphinxjp/themes/gopher/__init__.py
sphinxjp/themes/gopher/templates/gopher/layout.html
sphinxjp/themes/gopher/templates/gopher/theme.conf
sphinxjp/themes/gopher/templates/gopher/static/css/notes.css
sphinxjp/themes/gopher/templates/gopher/static/css/styles.css
sphinxjp/themes/gopher/templates/gopher/static/js/init.js
sphinxjp/themes/gopher/templates/gopher/static/js/notes.js
sphinxjp/themes/gopher/templates/gopher/static/js/slides.js
sphinxjp.themes.gopher-0.2.3.dist-info/METADATA
sphinxjp.themes.gopher-0.2.3.dist-info/WHEEL
sphinxjp.themes.gopher-0.2.3.dist-info/entry_points.txt
sphinxjp.themes.gopher-0.2.3.dist-info/namespace_packages.txt
sphinxjp.themes.gopher-0.2.3.dist-info/top_level.txt
sphinxjp.themes.gopher-0.2.3.dist-info/RECORD
