Metadata-Version: 2.1
Name: sphinxjp.themes.gopher
Version: 0.2.3
Summary: A sphinx theme for generate gotalk style presentation. #sphinxjp
Home-page: https://github.com/tell-k/sphinxjp.themes.gopher
Author: tell-k
Author-email: ffk2005@gmail.com
License: MIT
Keywords: sphinx,reStructuredText,theme,presentation
Platform: UNKNOWN
Classifier: Development Status :: 4 - Beta
Classifier: License :: OSI Approved :: MIT License
Classifier: Programming Language :: Python
Classifier: Programming Language :: Python :: 2
Classifier: Programming Language :: Python :: 2.7
Classifier: Programming Language :: Python :: 3
Classifier: Programming Language :: Python :: 3.4
Classifier: Programming Language :: Python :: 3.5
Classifier: Programming Language :: Python :: 3.6
Classifier: Programming Language :: Python :: 3.7
Classifier: Framework :: Sphinx
Classifier: Framework :: Sphinx :: Extension
Classifier: Framework :: Sphinx :: Theme
Classifier: Topic :: Software Development
Classifier: Topic :: Software Development :: Documentation
Classifier: Topic :: Text Processing :: Markup
Requires-Dist: Sphinx
